Metadata-Version: 1.0
Name: python-hiveish
Version: 1.0.10
Summary: A hive-like interface wrapper around Hadoopy that allows SQL like queries ontop of MapReduce directly from Python
Home-page: https://github.com/tommyjcarpenter/python-hiveish
Author: Tommy Carpenter
Author-email: tommyjcarpenter@gmail.com, tommy@research.att.com
License: MIT
Keywords: python,hadoop,mapreduce
Platform: UNKNOWN
